{
  "schemaVersion": 1,
  "version": "1.0.1-debug.6122",
  "tag": "v1.0.1-debug.6122+936f84d",
  "channel": "debug",
  "prerelease": true,
  "releaseSequence": 6122,
  "notes": "Automated release-signed debug-channel build from develop @ 936f84d. Push releases are always prerelease and never Latest.",
  "assets": [
    {
      "name": "hibiki-1.0.1-debug.6122-936f84d-debug.apk",
      "browser_download_url": "https://github.com/hajisensai/hibiki/releases/download/v1.0.1-debug.6122+936f84d/hibiki-1.0.1-debug.6122-936f84d-debug.apk"
    }
  ]
}
