{
  "schemaVersion": 1,
  "version": "0.11.1-debug.5616",
  "tag": "v0.11.1-debug.5616+84042a6",
  "channel": "debug",
  "prerelease": true,
  "releaseSequence": 5616,
  "notes": "Automated release-signed debug-channel build from develop @ 84042a6. Push releases are always prerelease and never Latest.",
  "assets": [
    {
      "name": "hibiki-0.11.1-debug.5616-84042a6-debug.apk",
      "browser_download_url": "https://github.com/hdjsadgfwtg/hibiki/releases/download/v0.11.1-debug.5616+84042a6/hibiki-0.11.1-debug.5616-84042a6-debug.apk"
    }
  ]
}
